{
"Test/AVL_Tree.test.cpp": "2020-09-07 16:22:32 +0900",
"Test/BinaryIndexedTree.test.cpp": "2020-09-07 16:22:32 +0900",
"Test/BinaryIndexedTree2D.test.cpp": "2020-09-07 16:22:32 +0900",
"Test/BinaryIndexedTree_RangeAdd.test.cpp": "2020-09-07 16:22:32 +0900",
"Test/BipartiteMatching.test.cpp": "2020-09-07 16:22:32 +0900",
"Test/CentroidDecomposition.test.cpp": "2020-09-07 16:22:32 +0900",
"Test/Dinic.test.cpp": "2020-09-07 16:22:32 +0900",
"Test/DisjointSparseTable.test.cpp": "2020-09-07 16:22:32 +0900",
"Test/EdmondsKarp.test.cpp": "2020-09-07 16:22:32 +0900",
"Test/FastFourierTransform_CookeyTukey-frequency-radix2.test.cpp": "2020-09-07 16:22:32 +0900",
"Test/FastFourierTransform_CookeyTukey-radix2.test.cpp": "2020-09-07 16:22:32 +0900",
"Test/FastFourierTransform_CookeyTukey-time-radix2.test.cpp": "2020-09-07 16:22:32 +0900",
"Test/FastFourierTransform_Real_CooleyTukey-frequency-radix2.test.cpp": "2020-09-07 16:22:32 +0900",
"Test/FastFourierTransform_Real_CooleyTukey-time-radix4.test.cpp": "2020-09-07 16:22:32 +0900",
"Test/HeavyLightDecomposition.test.cpp": "2020-09-07 16:22:32 +0900",
"Test/HeavyLightDecomposition_lca.test.cpp": "2020-09-07 16:22:32 +0900",
"Test/LazySegmentTree.test.cpp": "2020-09-11 13:51:33 +0900",
"Test/LowestCommonAncestor.test.cpp": "2020-09-07 16:22:32 +0900",
"Test/Matrix_Determinant.test.cpp": "2020-09-07 16:22:32 +0900",
"Test/NumberTheoreticTransform.test.cpp": "2020-09-07 16:22:32 +0900",
"Test/PersistentRedBlackTree.test.cpp": "2020-09-07 16:22:32 +0900",
"Test/PotentializedUnionFind.test.cpp": "2020-09-07 16:22:32 +0900",
"Test/PrimeNumber.counting_primes.test.cpp": "2020-09-08 16:59:22 +0900",
"Test/PrimeNumber.enumerate_primes.test.cpp": "2020-09-08 16:59:22 +0900",
"Test/RedBlackTree.test.cpp": "2020-09-07 16:22:32 +0900",
"Test/RollingHash.test.cpp": "2020-09-07 16:22:32 +0900",
"Test/SegmentTree.fold.test.cpp": "2020-09-07 16:22:32 +0900",
"Test/SparseTable.test.cpp": "2020-09-07 16:22:32 +0900",
"Test/StronglyConnectedComponents.test.cpp": "2020-09-10 10:57:52 +0900",
"Test/SuffixArray.lcp.test.cpp": "2020-09-08 10:02:39 +0900",
"Test/SuffixArray.sa_is.test.cpp": "2020-09-08 10:02:39 +0900",
"Test/SuffixArray.search.test.cpp": "2020-09-08 10:02:39 +0900",
"Test/TwoSat.test.cpp": "2020-09-10 10:57:52 +0900",
"Test/UnionFind.test.cpp": "2020-09-07 16:22:32 +0900",
"Test/WaveletMatrix.next_prev_value.test.cpp": "2020-09-07 21:36:42 +0900",
"Test/WaveletMatrix.quantile.test.cpp": "2020-09-07 21:36:42 +0900",
"Test/WaveletMatrix.range_frequency.test.cpp": "2020-09-07 21:36:42 +0900",
"Test/WaveletMatrix.select.test.cpp": "2020-09-07 21:36:42 +0900",
"Test/sum_of_floor_of_linear.test.cpp": "2020-09-11 08:54:48 +0900"
}